muffin_mongo/__init__.py
muffin_mongo/py.typed
muffin_mongo-0.6.1.dist-info/LICENSE
muffin_mongo-0.6.1.dist-info/METADATA
muffin_mongo-0.6.1.dist-info/WHEEL
muffin_mongo-0.6.1.dist-info/RECORD
