Metadata-Version: 2.1
Name: muffin-mongo
Version: 0.6.1
Summary: MongoDB support for Muffin framework.
Home-page: https://github.com/klen/muffin-mongo
License: MIT
Keywords: mongodb,muffin,asyncio,asgi,web
Author: Kirill Klenov
Author-email: horneds@gmail.com
Requires-Python: >=3.9,<4.0
Classifier: Development Status :: 5 - Production/Stable
Classifier: Framework :: AsyncIO
Classifier: Intended Audience :: Developers
Classifier: License :: OSI Approved :: MIT License
Classifier: Programming Language :: Python
Classifier: Programming Language :: Python :: 3
Classifier: Programming Language :: Python :: 3.9
Classifier: Programming Language :: Python :: 3.10
Classifier: Programming Language :: Python :: 3.11
Classifier: Programming Language :: Python :: 3.12
Requires-Dist: motor
Requires-Dist: muffin (>=0,<1)
Project-URL: Repository, https://github.com/klen/muffin-mongo
